mkdocstr/__init__.py
mkdocstr/cli.py
mkdocstr/docstring_generator.py
mkdocstr/langs/__init__.py
mkdocstr/langs/python.py
mkdocstr/languages.so
mkdocstr/output_styles/__init__.py
mkdocstr/output_styles/base.py
mkdocstr/output_styles/yasnippet.py
mkdocstr/tree_utils.py
mkdocstr/ttypes.py
mkdocstr/utils.py
mkdocstr-0.1.3.dist-info/entry_points.txt
mkdocstr-0.1.3.dist-info/WHEEL
mkdocstr-0.1.3.dist-info/METADATA
mkdocstr-0.1.3.dist-info/RECORD
