Metadata-Version: 2.1
Name: mkdocstr
Version: 0.1.3
Summary: 
Author: Jethro Kuan
Author-email: jethrokuan95@gmail.com
Requires-Python: >=3.8,<4.0
Classifier: Programming Language :: Python :: 3
Classifier: Programming Language :: Python :: 3.10
Classifier: Programming Language :: Python :: 3.8
Classifier: Programming Language :: Python :: 3.9
Requires-Dist: Mako (>=1.1.6,<2.0.0)
Requires-Dist: attrs (>=21.4.0,<22.0.0)
Requires-Dist: tree-sitter (>=0.20.0,<0.21.0)
